ShiyongJisuanjiShijueShizhanXiangmuJingtongOpencvChuyiFix1/README.md
ShiyongJisuanjiShijueShizhanXiangmuJingtongOpencvChuyiFix1/__init__.py
ShiyongJisuanjiShijueShizhanXiangmuJingtongOpencvChuyiFix1/__main__.py
ShiyongJisuanjiShijueShizhanXiangmuJingtongOpencvChuyiFix1/file.epub
ShiyongJisuanjiShijueShizhanXiangmuJingtongOpencvChuyiFix1/index.html
ShiyongJisuanjiShijueShizhanXiangmuJingtongOpencvChuyiFix1/css/__init__.py
ShiyongJisuanjiShijueShizhanXiangmuJingtongOpencvChuyiFix1/css/annotations.css
ShiyongJisuanjiShijueShizhanXiangmuJingtongOpencvChuyiFix1/css/main.css
ShiyongJisuanjiShijueShizhanXiangmuJingtongOpencvChuyiFix1/css/normalize.css
ShiyongJisuanjiShijueShizhanXiangmuJingtongOpencvChuyiFix1/css/popup.css
ShiyongJisuanjiShijueShizhanXiangmuJingtongOpencvChuyiFix1/font/__init__.py
ShiyongJisuanjiShijueShizhanXiangmuJingtongOpencvChuyiFix1/font/fontello.eot
ShiyongJisuanjiShijueShizhanXiangmuJingtongOpencvChuyiFix1/font/fontello.svg
ShiyongJisuanjiShijueShizhanXiangmuJingtongOpencvChuyiFix1/font/fontello.ttf
ShiyongJisuanjiShijueShizhanXiangmuJingtongOpencvChuyiFix1/font/fontello.woff
ShiyongJisuanjiShijueShizhanXiangmuJingtongOpencvChuyiFix1/img/__init__.py
ShiyongJisuanjiShijueShizhanXiangmuJingtongOpencvChuyiFix1/img/annotator-glyph-sprite.png
ShiyongJisuanjiShijueShizhanXiangmuJingtongOpencvChuyiFix1/img/annotator-icon-sprite.png
ShiyongJisuanjiShijueShizhanXiangmuJingtongOpencvChuyiFix1/img/apple-touch-icon.png
ShiyongJisuanjiShijueShizhanXiangmuJingtongOpencvChuyiFix1/img/cancelfullscreen.png
ShiyongJisuanjiShijueShizhanXiangmuJingtongOpencvChuyiFix1/img/close.png
ShiyongJisuanjiShijueShizhanXiangmuJingtongOpencvChuyiFix1/img/fullscreen.png
ShiyongJisuanjiShijueShizhanXiangmuJingtongOpencvChuyiFix1/img/loader.gif
ShiyongJisuanjiShijueShizhanXiangmuJingtongOpencvChuyiFix1/img/menu-icon.png
ShiyongJisuanjiShijueShizhanXiangmuJingtongOpencvChuyiFix1/img/save.png
ShiyongJisuanjiShijueShizhanXiangmuJingtongOpencvChuyiFix1/img/saved.png
shiyong_jisuanji_shijue_shizhan_xiangmu_jingtong_opencv_chuyi_fix1-2025.3.25.1.dist-info/METADATA
shiyong_jisuanji_shijue_shizhan_xiangmu_jingtong_opencv_chuyi_fix1-2025.3.25.1.dist-info/WHEEL
shiyong_jisuanji_shijue_shizhan_xiangmu_jingtong_opencv_chuyi_fix1-2025.3.25.1.dist-info/entry_points.txt
shiyong_jisuanji_shijue_shizhan_xiangmu_jingtong_opencv_chuyi_fix1-2025.3.25.1.dist-info/top_level.txt
shiyong_jisuanji_shijue_shizhan_xiangmu_jingtong_opencv_chuyi_fix1-2025.3.25.1.dist-info/RECORD
